[
  {
    "nanoid": "kkVzrzXzjFuUCN",
    "name": "Al Arabiya",
    "iptv_urls": [
      "https://live.alarabiya.net/alarabiapublish/alarabiya.smil/playlist.m3u8"
    ],
    "youtube_urls": [
      "https://www.youtube-nocookie.com/embed/n7eQejkXbnM"
    ],
    "language": "ara",
    "country": "ae",
    "isGeoBlocked": false
  },
  {
    "nanoid": "2TkyVV55zzBzz3",
    "name": "Al Arabiya Business",
    "iptv_urls": [
      "https://live.alarabiya.net/alarabiapublish/aswaaq.smil/playlist.m3u8"
    ],
    "youtube_urls": [],
    "language": "ara",
    "country": "ae",
    "isGeoBlocked": false
  },
  {
    "nanoid": "tn94bXCcZQXp4I",
    "name": "Al Arabiya Programs",
    "iptv_urls": [
      "https://d1j4r34gq3qw9y.cloudfront.net/out/v1/96804f3a14864641a21c25e8ca9afb74/index.m3u8"
    ],
    "youtube_urls": [],
    "language": "ara",
    "country": "ae",
    "isGeoBlocked": false
  },
  {
    "nanoid": "nm9j1gcFiJ0xm0",
    "name": "Al Dafrah TV",
    "iptv_urls": [
      "https://cdn-eu-west-prod-ingest-infra-dacast-com.akamaized.net/23cf2e00-28b0-b7b4-2569-ab7d19233fd7/index.m3u8"
    ],
    "youtube_urls": [],
    "language": "ara",
    "country": "ae",
    "isGeoBlocked": false
  },
  {
    "nanoid": "axtrtUohLCP3GM",
    "name": "Al Mashhad",
    "iptv_urls": [],
    "youtube_urls": [
      "https://www.youtube-nocookie.com/embed/iUXX-QQkR74"
    ],
    "language": "ara",
    "country": "ae",
    "isGeoBlocked": false
  },
  {
    "nanoid": "Y4O8X4bPqh2Vx5",
    "name": "Al Qamar TV",
    "iptv_urls": [
      "https://streamer3.premio.link/alqamar/playlist.m3u8"
    ],
    "youtube_urls": [],
    "language": "ara",
    "country": "ae",
    "isGeoBlocked": false
  },
  {
    "nanoid": "21EXltGyaMhzfR",
    "name": "Al Shallal TV",
    "iptv_urls": [
      "https://amg01480-alshallalfze-alshallal-ono-q0hfg.amagi.tv/playlist.m3u8"
    ],
    "youtube_urls": [],
    "language": "ara",
    "country": "ae",
    "isGeoBlocked": false
  },
  {
    "nanoid": "yR85LzOCV21lPt",
    "name": "Al Sharqiya Min Kabla",
    "iptv_urls": [
      "https://svs.itworkscdn.net/kablatvlive/kabtv1.smil/playlist.m3u8"
    ],
    "youtube_urls": [],
    "language": "ara",
    "country": "ae",
    "isGeoBlocked": false
  },
  {
    "nanoid": "U4Ytf8HCWlTZ0o",
    "name": "Al Wousta TV",
    "iptv_urls": [
      "https://svs.itworkscdn.net/alwoustalive/alwoustatv.smil/playlist.m3u8"
    ],
    "youtube_urls": [],
    "language": "ara",
    "country": "ae",
    "isGeoBlocked": false
  },
  {
    "nanoid": "YYEqzQiS4ARl9R",
    "name": "Al-Arabiya Business",
    "iptv_urls": [],
    "youtube_urls": [
      "https://www.youtube-nocookie.com/embed/rXnG4eiVVdM"
    ],
    "language": "ara",
    "country": "ae",
    "isGeoBlocked": false
  },
  {
    "nanoid": "ymEZZ9kXLlqF9g",
    "name": "Asharq Business اقتصاد الشرق",
    "iptv_urls": [],
    "youtube_urls": [
      "https://www.youtube-nocookie.com/embed/hXKYpuTEwqk"
    ],
    "language": "ara",
    "country": "ae",
    "isGeoBlocked": false
  },
  {
    "nanoid": "QFKHFoExvGyTwt",
    "name": "Cartoon Network",
    "iptv_urls": [],
    "youtube_urls": [
      "https://www.youtube-nocookie.com/embed/wK1e4ZXne8s",
      "https://www.youtube-nocookie.com/embed/k4VEBavsQ6g"
    ],
    "language": "ara",
    "country": "ae",
    "isGeoBlocked": false
  },
  {
    "nanoid": "rVlkWuhkPTSNkw",
    "name": "Cartoonito MENA",
    "iptv_urls": [],
    "youtube_urls": [
      "https://www.youtube-nocookie.com/embed/Koe1Dmep7fI"
    ],
    "language": "ara",
    "country": "ae",
    "isGeoBlocked": false
  },
  {
    "nanoid": "URU3r9PZvWBdLZ",
    "name": "CNBC Arabia",
    "iptv_urls": [],
    "youtube_urls": [
      "https://www.youtube-nocookie.com/embed/wYQuuzTJa1s"
    ],
    "language": "ara",
    "country": "ae",
    "isGeoBlocked": false
  },
  {
    "nanoid": "acbY5wCKKgtMnI",
    "name": "CNBC Arabiya",
    "iptv_urls": [
      "https://cnbc-live.akamaized.net/cnbc/master.m3u8"
    ],
    "youtube_urls": [],
    "language": "ara",
    "country": "ae",
    "isGeoBlocked": false
  },
  {
    "nanoid": "yf20BG1sxslF5N",
    "name": "Dubai One",
    "iptv_urls": [
      "https://dminnvllta.cdn.mgmlcdn.com/dubaione/smil:dubaione.stream.smil/chunklist.m3u8"
    ],
    "youtube_urls": [],
    "language": "eng",
    "country": "ae",
    "isGeoBlocked": false
  },
  {
    "nanoid": "gheSDFEMaPiSYU",
    "name": "Dubai Sports 1",
    "iptv_urls": [
      "https://dmidspta.cdn.mgmlcdn.com/dubaisports/smil:dubaisports.stream.smil/chunklist.m3u8"
    ],
    "youtube_urls": [],
    "language": "ara",
    "country": "ae",
    "isGeoBlocked": false
  },
  {
    "nanoid": "LDOUdB0YT96Fy3",
    "name": "Dubai Sports 2",
    "iptv_urls": [
      "https://dmitwlvvll.cdn.mgmlcdn.com/dubaisportshd/smil:dubaisportshd.smil/chunklist.m3u8"
    ],
    "youtube_urls": [],
    "language": "ara",
    "country": "ae",
    "isGeoBlocked": false
  },
  {
    "nanoid": "8fQhR4m1vT0J5n",
    "name": "Dubai Sports 3",
    "iptv_urls": [
      "https://dmitwlvvll.cdn.mgmlcdn.com/dubaisportshd5/smil:dubaisportshd5.smil/chunklist.m3u8"
    ],
    "youtube_urls": [],
    "language": "ara",
    "country": "ae",
    "isGeoBlocked": false
  },
  {
    "nanoid": "43meg58mA5npya",
    "name": "Dubai TV",
    "iptv_urls": [
      "https://dmieigthvllta.cdn.mgmlcdn.com/dubaitvht/smil:dubaitv.stream.smil/chunklist.m3u8"
    ],
    "youtube_urls": [],
    "language": "ara",
    "country": "ae",
    "isGeoBlocked": false
  },
  {
    "nanoid": "NpgtvD38qnisOV",
    "name": "Dubai Zaman",
    "iptv_urls": [
      "https://dmiffthftl.cdn.mangomolo.com/dubaizaman/smil:dubaizaman.stream.smil/chunklist.m3u8"
    ],
    "youtube_urls": [],
    "language": "ara",
    "country": "ae",
    "isGeoBlocked": false
  },
  {
    "nanoid": "NCWWidJrVWnWto",
    "name": "Fujairah TV",
    "iptv_urls": [
      "https://live.kwikmotion.com/fujairahlive/fujairah.smil/playlist.m3u8"
    ],
    "youtube_urls": [],
    "language": "ara",
    "country": "ae",
    "isGeoBlocked": false
  },
  {
    "nanoid": "T411svN9rFZRYL",
    "name": "MBC FM",
    "iptv_urls": [
      "https://dbbv9umqcd7cs.cloudfront.net/out/v1/db15b75c3cc0400c91961468d6a232ac/index.m3u8"
    ],
    "youtube_urls": [],
    "language": "eng",
    "country": "ae",
    "isGeoBlocked": false
  },
  {
    "nanoid": "UjnCLfmZ5c3yRj",
    "name": "MBC Persia",
    "iptv_urls": [
      "https://hls.mbcpersia.live/hls/stream.m3u8"
    ],
    "youtube_urls": [],
    "language": "fas",
    "country": "ae",
    "isGeoBlocked": false
  },
  {
    "nanoid": "tjO1W5XivBV60a",
    "name": "Nour TV",
    "iptv_urls": [
      "https://cdn.bestream.io:19360/elfaro4/elfaro4.m3u8"
    ],
    "youtube_urls": [],
    "language": "fas",
    "country": "ae",
    "isGeoBlocked": false
  },
  {
    "nanoid": "dwZ9cyjkWtVGIa",
    "name": "PMC Royale",
    "iptv_urls": [
      "https://pmcrohls.wns.live/hls/stream.m3u8"
    ],
    "youtube_urls": [],
    "language": "fas",
    "country": "ae",
    "isGeoBlocked": false
  },
  {
    "nanoid": "fmocYbtQ1fFZhn",
    "name": "Pulse95 Radio",
    "iptv_urls": [
      "https://svs.itworkscdn.net/pulse95live/pulse96/playlist.m3u8"
    ],
    "youtube_urls": [],
    "language": "ara",
    "country": "ae",
    "isGeoBlocked": false
  },
  {
    "nanoid": "we2YsCorQko3p5",
    "name": "Sama Dubai",
    "iptv_urls": [
      "https://dmieigthvllta.cdn.mgmlcdn.com/samadubaiht/smil:samadubai.stream.smil/chunklist.m3u8"
    ],
    "youtube_urls": [],
    "language": "ara",
    "country": "ae",
    "isGeoBlocked": false
  },
  {
    "nanoid": "OijQbjwV7a9kgP",
    "name": "Sharjah 2",
    "iptv_urls": [
      "https://svs.itworkscdn.net/smc2live/smc2tv.smil/playlist.m3u8"
    ],
    "youtube_urls": [],
    "language": "ara",
    "country": "ae",
    "isGeoBlocked": false
  },
  {
    "nanoid": "IhAqN9CcULw7M0",
    "name": "Sharjah Radio",
    "iptv_urls": [
      "https://svs.itworkscdn.net/smcradiolive/smcradiolive/playlist.m3u8"
    ],
    "youtube_urls": [],
    "language": "ara",
    "country": "ae",
    "isGeoBlocked": false
  },
  {
    "nanoid": "8RMhUftFipxVz5",
    "name": "Sharjah Radio Quran",
    "iptv_urls": [
      "https://live.kwikmotion.com/smcquranlive/quranradiolive/playlist.m3u8"
    ],
    "youtube_urls": [],
    "language": "ara",
    "country": "ae",
    "isGeoBlocked": false
  },
  {
    "nanoid": "PNu6nogB9kG5g5",
    "name": "Sharjah Sports",
    "iptv_urls": [
      "https://svs.itworkscdn.net/smc4sportslive/smc4.smil/playlist.m3u8",
      "https://svs.itworkscdn.net/smc4sportslive/smc4tv.smil/playlist.m3u8"
    ],
    "youtube_urls": [],
    "language": "ara",
    "country": "ae",
    "isGeoBlocked": false
  },
  {
    "nanoid": "RC2hZ1z0vrHMtE",
    "name": "Sharjah TV",
    "iptv_urls": [
      "https://live.kwikmotion.com/smc1live/smc1tv.smil/playlist.m3u8",
      "https://svs.itworkscdn.net/smc1live/smc1.smil/playlist.m3u8",
      "https://cdn-globecast.akamaized.net/live/eds/sharjah_tv/hls_roku/index.m3u8"
    ],
    "youtube_urls": [],
    "language": "ara",
    "country": "ae",
    "isGeoBlocked": false
  },
  {
    "nanoid": "lHA8lYSDtLC5LR",
    "name": "Sky News Arabia",
    "iptv_urls": [
      "https://stream.skynewsarabia.com/ott/ott.m3u8",
      "https://stream.skynewsarabia.com/hls/sna.m3u8"
    ],
    "youtube_urls": [],
    "language": "ara",
    "country": "ae",
    "isGeoBlocked": false
  },
  {
    "nanoid": "lHA8lYSDtLC5LR",
    "name": "Sky News Arabia",
    "iptv_urls": [
      "https://live-stream.skynewsarabia.com/c-horizontal-channel/horizontal-stream/index.m3u8"
    ],
    "youtube_urls": [
      "https://www.youtube-nocookie.com/embed/U--OjmpjF5o"
    ],
    "language": "",
    "country": "ae",
    "isGeoBlocked": false
  },
  {
    "nanoid": "54585W8guS2T76",
    "name": "Sky News Arabia (Portrait)",
    "iptv_urls": [
      "https://stream.skynewsarabia.com/vertical/vertical.m3u8"
    ],
    "youtube_urls": [],
    "language": "ara",
    "country": "ae",
    "isGeoBlocked": false
  },
  {
    "nanoid": "za3qiXgehwFjJ6",
    "name": "Sky News Arabia Vertical",
    "iptv_urls": [
      "https://live-stream.skynewsarabia.com/c-vertical-channel/vertical-stream/index.m3u8"
    ],
    "youtube_urls": [],
    "language": "",
    "country": "ae",
    "isGeoBlocked": false
  },
  {
    "nanoid": "mZmbWEboh9MGPf",
    "name": "The Smurfs: السنافر",
    "iptv_urls": [],
    "youtube_urls": [
      "https://www.youtube-nocookie.com/embed/ZtlLvu8H1OY"
    ],
    "language": "ara",
    "country": "ae",
    "isGeoBlocked": false
  },
  {
    "nanoid": "rbtvbfV1OrLd1T",
    "name": "Watar Radio",
    "iptv_urls": [
      "https://svs.itworkscdn.net/smcwatarlive/smcwatar/playlist.m3u8"
    ],
    "youtube_urls": [],
    "language": "ara",
    "country": "ae",
    "isGeoBlocked": false
  },
  {
    "nanoid": "SWuJf6pJ5H5SBG",
    "name": "اوكو ليلي القناة الرسمية 1",
    "iptv_urls": [],
    "youtube_urls": [
      "https://www.youtube-nocookie.com/embed/CAi0READ770"
    ],
    "language": "ara",
    "country": "ae",
    "isGeoBlocked": false
  }
]